easyllm/__init__.py
easyllm/core/__init__.py
easyllm/core/models/__init__.py
easyllm/core/models/embedding_model.py
easyllm/core/models/model.py
easyllm/core/models/providers.py
easyllm/utils/__init__.py
easyllm/utils/prompt.py
tests/test_ali.py
tests/test_prompt.py
python_easy_llm-0.1.2.dist-info/METADATA
python_easy_llm-0.1.2.dist-info/WHEEL
python_easy_llm-0.1.2.dist-info/top_level.txt
python_easy_llm-0.1.2.dist-info/RECORD
