Metadata-Version: 2.4
Name: python-easy-llm
Version: 0.1.2
Summary: A lightweight LLM wrapper that unifies prompt, RAG and multi-provider calls
Author-email: Chunyou Peng <chunyoupeng@gmail.com>
License: MIT
Classifier: Programming Language :: Python :: 3
Classifier: License :: OSI Approved :: MIT License
Classifier: Operating System :: OS Independent
Requires-Python: >=3.8
Requires-Dist: httpx>=0.27.0
Requires-Dist: openai
